two_factor/__init__.py
two_factor/admin.py
two_factor/apps.py
two_factor/forms.py
two_factor/signals.py
two_factor/urls.py
two_factor/utils.py
two_factor/gateways/__init__.py
two_factor/gateways/fake.py
two_factor/gateways/twilio/__init__.py
two_factor/gateways/twilio/gateway.py
two_factor/gateways/twilio/urls.py
two_factor/gateways/twilio/views.py
two_factor/locale/ar/LC_MESSAGES/django.mo
two_factor/locale/ar/LC_MESSAGES/django.po
two_factor/locale/as/LC_MESSAGES/django.mo
two_factor/locale/as/LC_MESSAGES/django.po
two_factor/locale/ca_ES/LC_MESSAGES/django.mo
two_factor/locale/ca_ES/LC_MESSAGES/django.po
two_factor/locale/cs/LC_MESSAGES/django.mo
two_factor/locale/cs/LC_MESSAGES/django.po
two_factor/locale/da_DK/LC_MESSAGES/django.mo
two_factor/locale/da_DK/LC_MESSAGES/django.po
two_factor/locale/de/LC_MESSAGES/django.mo
two_factor/locale/de/LC_MESSAGES/django.po
two_factor/locale/en/LC_MESSAGES/django.mo
two_factor/locale/en/LC_MESSAGES/django.po
two_factor/locale/en_GB/LC_MESSAGES/django.mo
two_factor/locale/en_GB/LC_MESSAGES/django.po
two_factor/locale/es/LC_MESSAGES/django.mo
two_factor/locale/es/LC_MESSAGES/django.po
two_factor/locale/fa/LC_MESSAGES/django.mo
two_factor/locale/fa/LC_MESSAGES/django.po
two_factor/locale/fi/LC_MESSAGES/django.mo
two_factor/locale/fi/LC_MESSAGES/django.po
two_factor/locale/fr/LC_MESSAGES/django.mo
two_factor/locale/fr/LC_MESSAGES/django.po
two_factor/locale/ha/LC_MESSAGES/django.mo
two_factor/locale/ha/LC_MESSAGES/django.po
two_factor/locale/he_IL/LC_MESSAGES/django.mo
two_factor/locale/he_IL/LC_MESSAGES/django.po
two_factor/locale/hi_IN/LC_MESSAGES/django.mo
two_factor/locale/hi_IN/LC_MESSAGES/django.po
two_factor/locale/hu_HU/LC_MESSAGES/django.mo
two_factor/locale/hu_HU/LC_MESSAGES/django.po
two_factor/locale/it/LC_MESSAGES/django.mo
two_factor/locale/it/LC_MESSAGES/django.po
two_factor/locale/ja/LC_MESSAGES/django.mo
two_factor/locale/ja/LC_MESSAGES/django.po
two_factor/locale/lt/LC_MESSAGES/django.mo
django_two_factor_auth-1.17.0.dist-info/LICENSE
django_two_factor_auth-1.17.0.dist-info/METADATA
django_two_factor_auth-1.17.0.dist-info/WHEEL
django_two_factor_auth-1.17.0.dist-info/top_level.txt
django_two_factor_auth-1.17.0.dist-info/RECORD
