Metadata-Version: 2.1
Name: django-two-factor-auth
Version: 1.17.0
Summary: Complete Two-Factor Authentication for Django
Author-email: Bouke Haarsma <bouke@haarsma.eu>
Maintainer-email: Claude Paroz <claude@2xlibre.net>, Matt Molyneaux <moggers87+git@moggers87.co.uk>
License: MIT
Project-URL: Homepage, https://github.com/jazzband/django-two-factor-auth
Project-URL: Documentation, https://django-two-factor-auth.readthedocs.io/en/stable/
Project-URL: Changelog, https://github.com/jazzband/django-two-factor-auth/blob/master/CHANGELOG.md
Keywords: django,two-factor
Classifier: Development Status :: 5 - Production/Stable
Classifier: Environment :: Web Environment
Classifier: Framework :: Django
Classifier: Framework :: Django :: 4.2
Classifier: Framework :: Django :: 5.0
Classifier: Framework :: Django :: 5.1
Classifier: Intended Audience :: Developers
Classifier: License :: OSI Approved :: MIT License
Classifier: Operating System :: OS Independent
Classifier: Programming Language :: Python
Classifier: Programming Language :: Python :: 3
Classifier: Programming Language :: Python :: 3 :: Only
Classifier: Programming Language :: Python :: 3.8
Classifier: Programming Language :: Python :: 3.9
Classifier: Programming Language :: Python :: 3.10
Classifier: Programming Language :: Python :: 3.11
Classifier: Programming Language :: Python :: 3.12
Classifier: Topic :: Security
Classifier: Topic :: System :: Systems Administration :: Authentication/Directory
Requires-Python: >=3.8
License-File: LICENSE
Requires-Dist: Django>=4.2
Requires-Dist: django_otp>=0.8.0
Requires-Dist: qrcode<7.99,>=4.0.0
Requires-Dist: django-phonenumber-field<9
Requires-Dist: django-formtools
Provides-Extra: call
Requires-Dist: twilio>=6.0; extra == "call"
Provides-Extra: sms
Requires-Dist: twilio>=6.0; extra == "sms"
Provides-Extra: webauthn
Requires-Dist: webauthn<2.99,>=2.0; extra == "webauthn"
Provides-Extra: yubikey
Requires-Dist: django-otp-yubikey; extra == "yubikey"
Provides-Extra: phonenumbers
Requires-Dist: phonenumbers<8.99,>=7.0.9; extra == "phonenumbers"
Provides-Extra: phonenumberslite
Requires-Dist: phonenumberslite<8.99,>=7.0.9; extra == "phonenumberslite"
Provides-Extra: tests
Requires-Dist: coverage; extra == "tests"
Requires-Dist: freezegun; extra == "tests"
Requires-Dist: tox; extra == "tests"
Provides-Extra: linting
Requires-Dist: ruff; extra == "linting"
Requires-Dist: isort<=5.99; extra == "linting"
